odoo8_addon_sale_validity-8.0.7.0.0.99.dev21-py3.8-nspkg.pth
odoo_addons/sale_validity/__init__.py
odoo_addons/sale_validity/__openerp__.py
odoo_addons/sale_validity/i18n/am.po
odoo_addons/sale_validity/i18n/ar.po
odoo_addons/sale_validity/i18n/bg.po
odoo_addons/sale_validity/i18n/bs.po
odoo_addons/sale_validity/i18n/ca.po
odoo_addons/sale_validity/i18n/cs.po
odoo_addons/sale_validity/i18n/da.po
odoo_addons/sale_validity/i18n/de.po
odoo_addons/sale_validity/i18n/el_GR.po
odoo_addons/sale_validity/i18n/es.po
odoo_addons/sale_validity/i18n/es_AR.po
odoo_addons/sale_validity/i18n/es_CL.po
odoo_addons/sale_validity/i18n/es_CO.po
odoo_addons/sale_validity/i18n/es_CR.po
odoo_addons/sale_validity/i18n/es_DO.po
odoo_addons/sale_validity/i18n/es_EC.po
odoo_addons/sale_validity/i18n/es_ES.po
odoo_addons/sale_validity/i18n/es_MX.po
odoo_addons/sale_validity/i18n/es_VE.po
odoo_addons/sale_validity/i18n/et.po
odoo_addons/sale_validity/i18n/fa.po
odoo_addons/sale_validity/i18n/fi.po
odoo_addons/sale_validity/i18n/fr.po
odoo_addons/sale_validity/i18n/fr_FR.po
odoo_addons/sale_validity/i18n/gl.po
odoo_addons/sale_validity/i18n/hr.po
odoo_addons/sale_validity/i18n/hr_HR.po
odoo_addons/sale_validity/i18n/hu.po
odoo_addons/sale_validity/i18n/id.po
odoo_addons/sale_validity/i18n/it.po
odoo_addons/sale_validity/i18n/ja.po
odoo_addons/sale_validity/i18n/ko.po
odoo_addons/sale_validity/i18n/lt.po
odoo_addons/sale_validity/i18n/lv.po
odoo_addons/sale_validity/i18n/mk.po
odoo_addons/sale_validity/i18n/mn.po
odoo_addons/sale_validity/i18n/nb.po
odoo_addons/sale_validity/i18n/nb_NO.po
odoo_addons/sale_validity/i18n/nl.po
odoo_addons/sale_validity/i18n/nl_BE.po
odoo_addons/sale_validity/i18n/nl_NL.po
odoo_addons/sale_validity/i18n/pl.po
odoo_addons/sale_validity/i18n/pt.po
odoo_addons/sale_validity/i18n/pt_BR.po
odoo_addons/sale_validity/i18n/ro.po
odoo_addons/sale_validity/i18n/ru.po
odoo_addons/sale_validity/i18n/sale_validity.pot
odoo_addons/sale_validity/i18n/sk.po
odoo8_addon_sale_validity-8.0.7.0.0.99.dev21.dist-info/METADATA
odoo8_addon_sale_validity-8.0.7.0.0.99.dev21.dist-info/WHEEL
odoo8_addon_sale_validity-8.0.7.0.0.99.dev21.dist-info/namespace_packages.txt
odoo8_addon_sale_validity-8.0.7.0.0.99.dev21.dist-info/top_level.txt
odoo8_addon_sale_validity-8.0.7.0.0.99.dev21.dist-info/RECORD
